{
  "case_count": 2,
  "cases": [
    {
      "asset": {
        "asset_id": "demo_port_01",
        "asset_name": "Demo Grain Port",
        "asset_type": "grain_port",
        "hero": true,
        "latitude": 46.501,
        "longitude": 30.747,
        "region": "Black Sea"
      },
      "baseline_frame": {
        "accepted_for_alerting": null,
        "baseline_frame_id": null,
        "filter_reason": null,
        "frame": {
          "asset_id": "demo_port_01",
          "captured_at": "2025-09-01T10:00:00Z",
          "cloud_cover": 0.03,
          "frame_id": "base_demo_port_01_20250901",
          "image_ref": "fixtures/demo_port_01/baseline-2025-09-01.png",
          "source": "sentinel_baseline_stub"
        },
        "overlay_ref": null
      },
      "case_id": "hero_port_disruption",
      "current_frame": {
        "accepted_for_alerting": null,
        "baseline_frame_id": "base_demo_port_01_20250901",
        "filter_reason": null,
        "frame": {
          "asset_id": "demo_port_01",
          "captured_at": "2026-04-14T18:40:00Z",
          "cloud_cover": 0.07,
          "frame_id": "cur_demo_port_01_20260414",
          "image_ref": "fixtures/demo_port_01/current-2026-04-14.png",
          "source": "sentinel_current_stub"
        },
        "overlay_ref": "fixtures/demo_port_01/overlay-2026-04-14.png"
      },
      "expected_action": "downlink_now",
      "expected_alert": {
        "action": "downlink_now",
        "alert_id": "blk_00017",
        "asset_id": "demo_port_01",
        "asset_name": "Demo Grain Port",
        "asset_type": "grain_port",
        "bbox": [
          0.19,
          0.26,
          0.73,
          0.84
        ],
        "civilian_impact": "shipping_or_aid_disruption",
        "confidence": 0.89,
        "event_type": "probable_large_scale_disruption",
        "mapbox_context_ref": null,
        "severity": "high",
        "source": {
          "baseline_frame_id": "base_demo_port_01_20250901",
          "current_frame_id": "cur_demo_port_01_20260414",
          "model_version": "lfm2.5-vl-450m-prompted"
        },
        "timestamp": "2026-04-14T18:40:00Z",
        "why": "Large terminal footprint change versus baseline near bulk loading berths."
      },
      "expected_candidate": {
        "action": "downlink_now",
        "bbox": [
          0.19,
          0.26,
          0.73,
          0.84
        ],
        "civilian_impact": "shipping_or_aid_disruption",
        "confidence": 0.89,
        "event_type": "probable_large_scale_disruption",
        "severity": "high",
        "why": "Large terminal footprint change versus baseline near bulk loading berths."
      },
      "expected_metrics": {
        "alerts_emitted": 5,
        "downlink_rate": 0.035,
        "frames_scanned": 143,
        "raw_frames_suppressed": 138
      },
      "hero": true,
      "model_output_text": "{\"event_type\": \"probable_large_scale_disruption\", \"severity\": \"high\", \"confidence\": 0.89, \"bbox\": [0.19, 0.26, 0.73, 0.84], \"civilian_impact\": \"shipping_or_aid_disruption\", \"why\": \"Large terminal footprint change versus baseline near bulk loading berths.\", \"action\": \"downlink_now\"}"
    },
    {
      "asset": {
        "asset_id": "demo_bridge_01",
        "asset_name": "Demo Logistics Bridge",
        "asset_type": "bridge",
        "hero": false,
        "latitude": 45.169,
        "longitude": 28.801,
        "region": "Lower Danube"
      },
      "baseline_frame": {
        "accepted_for_alerting": null,
        "baseline_frame_id": null,
        "filter_reason": null,
        "frame": {
          "asset_id": "demo_bridge_01",
          "captured_at": "2025-10-12T09:15:00Z",
          "cloud_cover": 0.02,
          "frame_id": "base_demo_bridge_01_20251012",
          "image_ref": "fixtures/demo_bridge_01/baseline-2025-10-12.png",
          "source": "sentinel_baseline_stub"
        },
        "overlay_ref": null
      },
      "case_id": "bridge_access_obstruction",
      "current_frame": {
        "accepted_for_alerting": null,
        "baseline_frame_id": "base_demo_bridge_01_20251012",
        "filter_reason": null,
        "frame": {
          "asset_id": "demo_bridge_01",
          "captured_at": "2026-04-14T18:42:00Z",
          "cloud_cover": 0.05,
          "frame_id": "cur_demo_bridge_01_20260414",
          "image_ref": "fixtures/demo_bridge_01/current-2026-04-14.png",
          "source": "sentinel_current_stub"
        },
        "overlay_ref": "fixtures/demo_bridge_01/overlay-2026-04-14.png"
      },
      "expected_action": "defer",
      "expected_alert": {
        "action": "defer",
        "alert_id": "blk_00018",
        "asset_id": "demo_bridge_01",
        "asset_name": "Demo Logistics Bridge",
        "asset_type": "bridge",
        "bbox": [
          0.31,
          0.18,
          0.68,
          0.71
        ],
        "civilian_impact": "public_mobility_disruption",
        "confidence": 0.78,
        "event_type": "probable_access_obstruction",
        "mapbox_context_ref": null,
        "severity": "medium",
        "source": {
          "baseline_frame_id": "base_demo_bridge_01_20251012",
          "current_frame_id": "cur_demo_bridge_01_20260414",
          "model_version": "lfm2.5-vl-450m-prompted"
        },
        "timestamp": "2026-04-14T18:42:00Z",
        "why": "Bridge deck access appears partially obstructed versus stable baseline."
      },
      "expected_candidate": {
        "action": "defer",
        "bbox": [
          0.31,
          0.18,
          0.68,
          0.71
        ],
        "civilian_impact": "public_mobility_disruption",
        "confidence": 0.78,
        "event_type": "probable_access_obstruction",
        "severity": "medium",
        "why": "Bridge deck access appears partially obstructed versus stable baseline."
      },
      "expected_metrics": {
        "alerts_emitted": 2,
        "downlink_rate": 0.023,
        "frames_scanned": 88,
        "raw_frames_suppressed": 86
      },
      "hero": false,
      "model_output_text": "{\"event_type\": \"probable_access_obstruction\", \"severity\": \"medium\", \"confidence\": 0.78, \"bbox\": [0.31, 0.18, 0.68, 0.71], \"civilian_impact\": \"public_mobility_disruption\", \"why\": \"Bridge deck access appears partially obstructed versus stable baseline.\", \"action\": \"defer\"}"
    }
  ],
  "pack_version": "hero-replay-v1"
}
